bitbridge/__init__.py
bitbridge/facade.py
bitbridge/rpc_delegate.py
bitbridge/rpc/__init__.py
bitbridge/rpc/base_rpc.py
bitbridge/rpc/blockchain.py
bitbridge/rpc/config.py
bitbridge/rpc/generate.py
bitbridge/rpc/raw_transaction.py
bitbridge/rpc/util.py
bitbridge/rpc/wallet.py
bitbridge/utils/__init__.py
bitbridge/utils/constants.py
bitbridge/utils/decorators.py
bitbridge/utils/enums.py
bitbridge/utils/exceptions.py
bitbridge/utils/helpers.py
bitbridge/utils/logger.py
bitbridge-0.3.5.dist-info/METADATA
bitbridge-0.3.5.dist-info/WHEEL
bitbridge-0.3.5.dist-info/licenses/LICENSE
bitbridge-0.3.5.dist-info/RECORD
