Metadata-Version: 2.1
Name: BitBridge
Version: 0.3.5
Summary: A modern Python interface to the Bitcoin Core RPC, offering both synchronous and asynchronous support.
Project-URL: Homepage, https://github.com/godd0t/bitbridge
Author-email: godd0t <lirrishala@gmail.com>
License: MIT
License-File: LICENSE
Classifier: Development Status :: 1 - Planning
Classifier: Environment :: Web Environment
Classifier: Intended Audience :: Developers
Classifier: License :: OSI Approved :: MIT License
Classifier: Operating System :: OS Independent
Classifier: Programming Language :: Python :: 3.11
Classifier: Topic :: Software Development :: Libraries :: Python Modules
Classifier: Topic :: Software Development :: Version Control :: Git
Classifier: Topic :: Utilities
Requires-Python: >=3.10
Requires-Dist: httpx>=0.24.1
Requires-Dist: rich>=13.5.2
Provides-Extra: lint
Requires-Dist: black>=23.7.0; extra == 'lint'
Requires-Dist: ruff>=0.0.287; extra == 'lint'
Provides-Extra: test
Requires-Dist: coverage[toml]>=7.3.0; extra == 'test'
Requires-Dist: faker>=19.3.1; extra == 'test'
Requires-Dist: pytest-asyncio>=0.21.1; extra == 'test'
Requires-Dist: pytest-sugar>=0.9.7; extra == 'test'
Requires-Dist: pytest>=7.4.1; extra == 'test'
